application_properties/.external-package
application_properties/__init__.py
application_properties/application_properties.py
application_properties/application_properties_config_loader.py
application_properties/application_properties_facade.py
application_properties/application_properties_json_loader.py
application_properties/application_properties_loader_helper.py
application_properties/application_properties_toml_loader.py
application_properties/application_properties_utilities.py
application_properties/application_properties_yaml_loader.py
application_properties/multisource_configuration_loader.py
application_properties/py.typed
application_properties/version.py
application_properties-0.9.1.dist-info/licenses/LICENSE.txt
application_properties-0.9.1.dist-info/METADATA
application_properties-0.9.1.dist-info/WHEEL
application_properties-0.9.1.dist-info/top_level.txt
application_properties-0.9.1.dist-info/RECORD
